solarman_opendata/_init_.py
solarman_opendata/const.py
solarman_opendata/errors.py
solarman_opendata/solarman.py
solarman_opendata/utils.py
solarman_opendata-0.0.1.dist-info/licenses/LICENSE
solarman_opendata-0.0.1.dist-info/METADATA
solarman_opendata-0.0.1.dist-info/WHEEL
solarman_opendata-0.0.1.dist-info/top_level.txt
solarman_opendata-0.0.1.dist-info/RECORD
