Metadata-Version: 2.4
Name: solarman-opendata
Version: 0.0.1
Summary: Asynchronous Python API for Solarman devices
Author-email: solarmanpv <info@solarmanpv.com>
License-Expression: Apache-2.0
Project-URL: Homepage, https://github.com/solarmanpv/solarman-opendata
Project-URL: Repository, https://github.com/solarmanpv/solarman-opendata
Project-URL: Issues, https://github.com/solarmanpv/solarman-opendata/issues
Keywords: solarman,iot,home automation
Classifier: Intended Audience :: Developers
Classifier: Topic :: Home Automation
Classifier: Topic :: Software Development :: Libraries :: Python Modules
Classifier: Programming Language :: Python :: 3
Classifier: Programming Language :: Python :: 3.12
Classifier: Operating System :: OS Independent
Requires-Python: >=3.12
License-File: LICENSE
Requires-Dist: aiohttp>=3.8.0
Provides-Extra: dev
Requires-Dist: pytest>=7.0; extra == "dev"
Requires-Dist: pytest-asyncio>=0.21.0; extra == "dev"
Requires-Dist: pytest-mock>=3.10.0; extra == "dev"
Requires-Dist: flake8>=6.0.0; extra == "dev"
Requires-Dist: mypy>=1.0.0; extra == "dev"
Requires-Dist: black>=23.0.0; extra == "dev"
Requires-Dist: isort>=5.12.0; extra == "dev"
Requires-Dist: types-requests>=2.31.0; extra == "dev"
Dynamic: license-file
